hl7find/__init__.py
hl7find/hl7find.py
hl7find-1.0.2.dist-info/METADATA
hl7find-1.0.2.dist-info/WHEEL
hl7find-1.0.2.dist-info/licenses/LICENSE
hl7find-1.0.2.dist-info/RECORD
