Metadata-Version: 2.3
Name: hl7find
Version: 1.0.2
Summary: An easy to use HL7 v2 parsing library based on typical hl7 notiation (e.g. PID.3.1)
Project-URL: Homepage, https://github.com/mwarnock/hl7find
Project-URL: Issues, https://github.com/mwarnock/hl7find/issues
Author-email: Max Warnock <maxjwarnock@gmail.com>
Classifier: License :: OSI Approved :: MIT License
Classifier: Operating System :: OS Independent
Classifier: Programming Language :: Python :: 3
Requires-Python: >=3.8
